{
  "name": "com.instituto.api.repository.InvestigadorRepository",
  "module": "JPA",
  "type": "IMPERATIVE",
  "methods": [
    {
      "name": "findByArea",
      "signature": "public abstract java.util.List<com.instituto.api.entity.Investigador> com.instituto.api.repository.InvestigadorRepository.findByArea(com.instituto.api.entity.AreaInvestigacion)",
      "query": {
        "query": "SELECT i FROM Investigador i WHERE i.area = :area"
      }
    },
    {
      "name": "findByEspecialidad",
      "signature": "public abstract java.util.List<com.instituto.api.entity.Investigador> com.instituto.api.repository.InvestigadorRepository.findByEspecialidad(java.lang.String)",
      "query": {
        "query": "SELECT i FROM Investigador i WHERE i.especialidad = :especialidad"
      }
    },
    {
      "name": "deleteAllByIdInBatch",
      "signature": "org.springframework.data.jpa.repository.support.SimpleJpaRepository",
      "fragment": {
        "interface": "org.springframework.data.jpa.repository.support.SimpleJpaRepository",
        "fragment": "org.springframework.data.jpa.repository.support.SimpleJpaRepository"
      }
    },
    {
      "name": "deleteAllInBatch",
      "signature": "org.springframework.data.jpa.repository.support.SimpleJpaRepository",
      "fragment": {
        "interface": "org.springframework.data.jpa.repository.support.SimpleJpaRepository",
        "fragment": "org.springframework.data.jpa.repository.support.SimpleJpaRepository"
      }
    },
    {
      "name": "deleteAllInBatch",
      "signature": "org.springframework.data.jpa.repository.support.SimpleJpaRepository",
      "fragment": {
        "interface": "org.springframework.data.jpa.repository.support.SimpleJpaRepository",
        "fragment": "org.springframework.data.jpa.repository.support.SimpleJpaRepository"
      }
    },
    {
      "name": "deleteInBatch",
      "signature": "org.springframework.data.jpa.repository.support.SimpleJpaRepository",
      "fragment": {
        "interface": "org.springframework.data.jpa.repository.support.SimpleJpaRepository",
        "fragment": "org.springframework.data.jpa.repository.support.SimpleJpaRepository"
      }
    },
    {
      "name": "findAll",
      "signature": "org.springframework.data.jpa.repository.support.SimpleJpaRepository",
      "fragment": {
        "interface": "org.springframework.data.jpa.repository.support.SimpleJpaRepository",
        "fragment": "org.springframework.data.jpa.repository.support.SimpleJpaRepository"
      }
    },
    {
      "name": "findAll",
      "signature": "org.springframework.data.jpa.repository.support.SimpleJpaRepository",
      "fragment": {
        "interface": "org.springframework.data.jpa.repository.support.SimpleJpaRepository",
        "fragment": "org.springframework.data.jpa.repository.support.SimpleJpaRepository"
      }
    },
    {
      "name": "findAll",
      "signature": "org.springframework.data.jpa.repository.support.SimpleJpaRepository",
      "fragment": {
        "interface": "org.springframework.data.jpa.repository.support.SimpleJpaRepository",
        "fragment": "org.springframework.data.jpa.repository.support.SimpleJpaRepository"
      }
    },
    {
      "name": "findAll",
      "signature": "org.springframework.data.jpa.repository.support.SimpleJpaRepository",
      "fragment": {
        "interface": "org.springframework.data.jpa.repository.support.SimpleJpaRepository",
        "fragment": "org.springframework.data.jpa.repository.support.SimpleJpaRepository"
      }
    },
    {
      "name": "flush",
      "signature": "org.springframework.data.jpa.repository.support.SimpleJpaRepository",
      "fragment": {
        "interface": "org.springframework.data.jpa.repository.support.SimpleJpaRepository",
        "fragment": "org.springframework.data.jpa.repository.support.SimpleJpaRepository"
      }
    },
    {
      "name": "getById",
      "signature": "org.springframework.data.jpa.repository.support.SimpleJpaRepository",
      "fragment": {
        "interface": "org.springframework.data.jpa.repository.support.SimpleJpaRepository",
        "fragment": "org.springframework.data.jpa.repository.support.SimpleJpaRepository"
      }
    },
    {
      "name": "getOne",
      "signature": "org.springframework.data.jpa.repository.support.SimpleJpaRepository",
      "fragment": {
        "interface": "org.springframework.data.jpa.repository.support.SimpleJpaRepository",
        "fragment": "org.springframework.data.jpa.repository.support.SimpleJpaRepository"
      }
    },
    {
      "name": "getReferenceById",
      "signature": "org.springframework.data.jpa.repository.support.SimpleJpaRepository",
      "fragment": {
        "interface": "org.springframework.data.jpa.repository.support.SimpleJpaRepository",
        "fragment": "org.springframework.data.jpa.repository.support.SimpleJpaRepository"
      }
    },
    {
      "name": "saveAllAndFlush",
      "signature": "org.springframework.data.jpa.repository.support.SimpleJpaRepository",
      "fragment": {
        "interface": "org.springframework.data.jpa.repository.support.SimpleJpaRepository",
        "fragment": "org.springframework.data.jpa.repository.support.SimpleJpaRepository"
      }
    },
    {
      "name": "saveAndFlush",
      "signature": "org.springframework.data.jpa.repository.support.SimpleJpaRepository",
      "fragment": {
        "interface": "org.springframework.data.jpa.repository.support.SimpleJpaRepository",
        "fragment": "org.springframework.data.jpa.repository.support.SimpleJpaRepository"
      }
    },
    {
      "name": "count",
      "signature": "org.springframework.data.jpa.repository.support.SimpleJpaRepository",
      "fragment": {
        "interface": "org.springframework.data.jpa.repository.support.SimpleJpaRepository",
        "fragment": "org.springframework.data.jpa.repository.support.SimpleJpaRepository"
      }
    },
    {
      "name": "delete",
      "signature": "org.springframework.data.jpa.repository.support.SimpleJpaRepository",
      "fragment": {
        "interface": "org.springframework.data.jpa.repository.support.SimpleJpaRepository",
        "fragment": "org.springframework.data.jpa.repository.support.SimpleJpaRepository"
      }
    },
    {
      "name": "deleteAll",
      "signature": "org.springframework.data.jpa.repository.support.SimpleJpaRepository",
      "fragment": {
        "interface": "org.springframework.data.jpa.repository.support.SimpleJpaRepository",
        "fragment": "org.springframework.data.jpa.repository.support.SimpleJpaRepository"
      }
    },
    {
      "name": "deleteAll",
      "signature": "org.springframework.data.jpa.repository.support.SimpleJpaRepository",
      "fragment": {
        "interface": "org.springframework.data.jpa.repository.support.SimpleJpaRepository",
        "fragment": "org.springframework.data.jpa.repository.support.SimpleJpaRepository"
      }
    },
    {
      "name": "deleteAllById",
      "signature": "org.springframework.data.jpa.repository.support.SimpleJpaRepository",
      "fragment": {
        "interface": "org.springframework.data.jpa.repository.support.SimpleJpaRepository",
        "fragment": "org.springframework.data.jpa.repository.support.SimpleJpaRepository"
      }
    },
    {
      "name": "deleteById",
      "signature": "org.springframework.data.jpa.repository.support.SimpleJpaRepository",
      "fragment": {
        "interface": "org.springframework.data.jpa.repository.support.SimpleJpaRepository",
        "fragment": "org.springframework.data.jpa.repository.support.SimpleJpaRepository"
      }
    },
    {
      "name": "existsById",
      "signature": "org.springframework.data.jpa.repository.support.SimpleJpaRepository",
      "fragment": {
        "interface": "org.springframework.data.jpa.repository.support.SimpleJpaRepository",
        "fragment": "org.springframework.data.jpa.repository.support.SimpleJpaRepository"
      }
    },
    {
      "name": "findById",
      "signature": "org.springframework.data.jpa.repository.support.SimpleJpaRepository",
      "fragment": {
        "interface": "org.springframework.data.jpa.repository.support.SimpleJpaRepository",
        "fragment": "org.springframework.data.jpa.repository.support.SimpleJpaRepository"
      }
    },
    {
      "name": "save",
      "signature": "org.springframework.data.jpa.repository.support.SimpleJpaRepository",
      "fragment": {
        "interface": "org.springframework.data.jpa.repository.support.SimpleJpaRepository",
        "fragment": "org.springframework.data.jpa.repository.support.SimpleJpaRepository"
      }
    },
    {
      "name": "findAll",
      "signature": "org.springframework.data.jpa.repository.support.SimpleJpaRepository",
      "fragment": {
        "interface": "org.springframework.data.jpa.repository.support.SimpleJpaRepository",
        "fragment": "org.springframework.data.jpa.repository.support.SimpleJpaRepository"
      }
    },
    {
      "name": "findAll",
      "signature": "org.springframework.data.jpa.repository.support.SimpleJpaRepository",
      "fragment": {
        "interface": "org.springframework.data.jpa.repository.support.SimpleJpaRepository",
        "fragment": "org.springframework.data.jpa.repository.support.SimpleJpaRepository"
      }
    },
    {
      "name": "findAllById",
      "signature": "org.springframework.data.jpa.repository.support.SimpleJpaRepository",
      "fragment": {
        "interface": "org.springframework.data.jpa.repository.support.SimpleJpaRepository",
        "fragment": "org.springframework.data.jpa.repository.support.SimpleJpaRepository"
      }
    },
    {
      "name": "findAllById",
      "signature": "org.springframework.data.jpa.repository.support.SimpleJpaRepository",
      "fragment": {
        "interface": "org.springframework.data.jpa.repository.support.SimpleJpaRepository",
        "fragment": "org.springframework.data.jpa.repository.support.SimpleJpaRepository"
      }
    },
    {
      "name": "saveAll",
      "signature": "org.springframework.data.jpa.repository.support.SimpleJpaRepository",
      "fragment": {
        "interface": "org.springframework.data.jpa.repository.support.SimpleJpaRepository",
        "fragment": "org.springframework.data.jpa.repository.support.SimpleJpaRepository"
      }
    },
    {
      "name": "saveAll",
      "signature": "org.springframework.data.jpa.repository.support.SimpleJpaRepository",
      "fragment": {
        "interface": "org.springframework.data.jpa.repository.support.SimpleJpaRepository",
        "fragment": "org.springframework.data.jpa.repository.support.SimpleJpaRepository"
      }
    },
    {
      "name": "findAll",
      "signature": "org.springframework.data.jpa.repository.support.SimpleJpaRepository",
      "fragment": {
        "interface": "org.springframework.data.jpa.repository.support.SimpleJpaRepository",
        "fragment": "org.springframework.data.jpa.repository.support.SimpleJpaRepository"
      }
    },
    {
      "name": "findAll",
      "signature": "org.springframework.data.jpa.repository.support.SimpleJpaRepository",
      "fragment": {
        "interface": "org.springframework.data.jpa.repository.support.SimpleJpaRepository",
        "fragment": "org.springframework.data.jpa.repository.support.SimpleJpaRepository"
      }
    },
    {
      "name": "findAll",
      "signature": "org.springframework.data.jpa.repository.support.SimpleJpaRepository",
      "fragment": {
        "interface": "org.springframework.data.jpa.repository.support.SimpleJpaRepository",
        "fragment": "org.springframework.data.jpa.repository.support.SimpleJpaRepository"
      }
    },
    {
      "name": "count",
      "signature": "org.springframework.data.jpa.repository.support.SimpleJpaRepository",
      "fragment": {
        "interface": "org.springframework.data.jpa.repository.support.SimpleJpaRepository",
        "fragment": "org.springframework.data.jpa.repository.support.SimpleJpaRepository"
      }
    },
    {
      "name": "exists",
      "signature": "org.springframework.data.jpa.repository.support.SimpleJpaRepository",
      "fragment": {
        "interface": "org.springframework.data.jpa.repository.support.SimpleJpaRepository",
        "fragment": "org.springframework.data.jpa.repository.support.SimpleJpaRepository"
      }
    },
    {
      "name": "findAll",
      "signature": "org.springframework.data.jpa.repository.support.SimpleJpaRepository",
      "fragment": {
        "interface": "org.springframework.data.jpa.repository.support.SimpleJpaRepository",
        "fragment": "org.springframework.data.jpa.repository.support.SimpleJpaRepository"
      }
    },
    {
      "name": "findBy",
      "signature": "org.springframework.data.jpa.repository.support.SimpleJpaRepository",
      "fragment": {
        "interface": "org.springframework.data.jpa.repository.support.SimpleJpaRepository",
        "fragment": "org.springframework.data.jpa.repository.support.SimpleJpaRepository"
      }
    },
    {
      "name": "findOne",
      "signature": "org.springframework.data.jpa.repository.support.SimpleJpaRepository",
      "fragment": {
        "interface": "org.springframework.data.jpa.repository.support.SimpleJpaRepository",
        "fragment": "org.springframework.data.jpa.repository.support.SimpleJpaRepository"
      }
    }
  ]
}